{"nome":"AGRA INCORP","cnpj":"07.698.047/0001-10","site":"www.agra.com.br/ri","balanco_patrimonial":{"periodo":["31/03/2010<","31/12/2009<"],"ativo_permanente":[],"ativo_total":["2.241.937<","2.116.377<"],"patromonio_liquido":["1.028.215<","999.805<"]},"demonstracao_do_resultado":{"periodo":["01/01/2010 a 31/03/2010<","01/01/2009 a 31/03/2009<"],"receitas_da_intermediacao_financeira":[],"resultado_bruto_de_intermediacao_financeira":[],"resultado_operacional":["31.274<","10.974<"],"lucro_liquido":["28.106<","9.686<"]},"demonstracao_do_fluxo_de_caixa":{"periodo":["01/01/2010 a 31/03/2010<","01/01/2009 a 31/03/2009<"],"atividades_operacionais":["(124.228)<","(44.281)<"],"atividades_de_investimento":["(5.174)<","(3.116)<"],"atividades_de_financiamento":["178.108<","(31.662)<"],"variacao_cambial_sobre_caixa_e_equivalentes":["0<","0<"],"aumento_de_caixa_e_equivalentes":["48.706<","(79.059)<"]},"posicao_acionaria":{"headings":["%ON<","%PN<","%Total<"],"outros":["50,20<","0,00<","50,20<"],"total":["100,00<","0,00<","100,00<"]},"composicao_capital_social":{"data":"22/12/2008","ordinarias":">239.296.539","preferenciais":">0","total":">239.296.539"}}