{"nome":"ALUPAR","cnpj":"08.364.948/0001-38","site":"www.alupar.com.br","balanco_patrimonial":{"periodo":["<                    ","31/03/2018<"],"ativo_permanente":[],"ativo_total":["11.143.590<","11.463.372<"],"patromonio_liquido":["5.676.825<","5.606.797<"]},"demonstracao_do_resultado":{"periodo":["01/01/2018 a 31/03/2018<","01/01/2017 a 31/03/2017<"],"receitas_da_intermediacao_financeira":[],"resultado_bruto_de_intermediacao_financeira":[],"resultado_operacional":[],"lucro_liquido":[]},"demonstracao_do_fluxo_de_caixa":{"periodo":["01/01/2018 a 31/03/2018<","01/01/2017 a 31/03/2017<"],"atividades_operacionais":["241.269<","237.371<"],"atividades_de_investimento":["16.791<","(58.867)<"],"atividades_de_financiamento":["(608.851)<","(284.930)<"],"variacao_cambial_sobre_caixa_e_equivalentes":["(13.892)<","(1.013)<"],"aumento_de_caixa_e_equivalentes":["(364.683)<","(107.439)<"]},"posicao_acionaria":{"headings":["%ON<","%PN<","%Total<"],"outros":["15,85<","67,10<","32,30<"],"total":["100,00<","100,00<","100,00<"]},"composicao_capital_social":{"data":"11/06/18","ordinarias":">150.960.603","preferenciais":">269.684.171","total":">879.111.269"}}