{"nome":"ARTHUR LANGE","cnpj":"92.189.356/0001-33","site":"","balanco_patrimonial":{"periodo":["31/12/2008<","31/12/2007<"],"ativo_permanente":[],"ativo_total":["26.946<","34.649<"],"patromonio_liquido":["(39.704)<","(20.870)<"]},"demonstracao_do_resultado":{"periodo":["<8002/21/13 a 8002/10/10>ht<                                ","<7002/21/13 a 7002/10/10>ht<                                "],"receitas_da_intermediacao_financeira":[],"resultado_bruto_de_intermediacao_financeira":[],"resultado_operacional":["(6.914)<","(2.910)<"],"lucro_liquido":["(18.833)<","(5.806)<"]},"demonstracao_do_fluxo_de_caixa":{"periodo":["01/01/2008 a 31/12/2008<","01/01/2007 a 31/12/2007<"],"atividades_operacionais":["(2.315)<","1.097<"],"atividades_de_investimento":["76<","(13)<"],"atividades_de_financiamento":["2.204<","(1.063)<"],"variacao_cambial_sobre_caixa_e_equivalentes":["0<","0<"],"aumento_de_caixa_e_equivalentes":["(35)<","21<"]},"posicao_acionaria":{"headings":[],"outros":[],"total":[]},"composicao_capital_social":{"data":"28/04/2006","ordinarias":">2.230.630","preferenciais":">2.229.473","total":">4.460.103"}}