{"nome":"AZUL","cnpj":"09.305.994/0001-29","site":"www.voeazul.com.br","balanco_patrimonial":{"periodo":["<                    ","31/03/2018<"],"ativo_permanente":[],"ativo_total":["10.401.318<","10.316.616<"],"patromonio_liquido":["3.018.717<","2.833.610<"]},"demonstracao_do_resultado":{"periodo":["01/01/2018 a 31/03/2018<","01/01/2017 a 31/03/2017<"],"receitas_da_intermediacao_financeira":[],"resultado_bruto_de_intermediacao_financeira":[],"resultado_operacional":[],"lucro_liquido":[]},"demonstracao_do_fluxo_de_caixa":{"periodo":["01/01/2018 a 31/03/2018<","01/01/2017 a 31/03/2017<"],"atividades_operacionais":["(259.947)<","26.183<"],"atividades_de_investimento":["367.466<","125.961<"],"atividades_de_financiamento":["(134.412)<","(262.028)<"],"variacao_cambial_sobre_caixa_e_equivalentes":["3.514<","(4.310)<"],"aumento_de_caixa_e_equivalentes":["(23.379)<","(114.194)<"]},"posicao_acionaria":{"headings":["%ON<","%PN<","%Total<"],"outros":["0,00<","56,93<","14,72<"],"total":["100,00<","100,00<","100,00<"]},"composicao_capital_social":{"data":"11/06/18","ordinarias":">306.558.420","preferenciais":">315.738.677","total":">1.252.930.395"}}