{"nome":"DIRECIONAL","cnpj":"16.614.075/0001-00","site":"www.direcional.com.br/ri","balanco_patrimonial":{"periodo":["<                    ","31/03/2018<"],"ativo_permanente":[],"ativo_total":["4.235.185<","4.141.764<"],"patromonio_liquido":["1.601.642<","1.604.315<"]},"demonstracao_do_resultado":{"periodo":["01/01/2018 a 31/03/2018<","01/01/2017 a 31/03/2017<"],"receitas_da_intermediacao_financeira":[],"resultado_bruto_de_intermediacao_financeira":[],"resultado_operacional":[],"lucro_liquido":[]},"demonstracao_do_fluxo_de_caixa":{"periodo":["01/01/2018 a 31/03/2018<","01/01/2017 a 31/03/2017<"],"atividades_operacionais":["6.446<","(898)<"],"atividades_de_investimento":["(93.820)<","59.699<"],"atividades_de_financiamento":["107.062<","(113.952)<"],"variacao_cambial_sobre_caixa_e_equivalentes":["0<","0<"],"aumento_de_caixa_e_equivalentes":["19.688<","(55.151)<"]},"posicao_acionaria":{"headings":["%ON<","%PN<","%Total<"],"outros":["39,80<","0,00<","39,80<"],"total":["100,00<","0,00<","100,00<"]},"composicao_capital_social":{"data":"07/05/2015","ordinarias":">75.584.315","preferenciais":">0","total":">153.398.749"}}