{"nome":"DURATEX","cnpj":"61.194.080/0001-58","site":"www.duratex.com.br","balanco_patrimonial":{"periodo":["30/06/2009<","31/03/2009<"],"ativo_permanente":[],"ativo_total":["3.249.018<","3.239.646<"],"patromonio_liquido":["1.789.980<","1.758.513<"]},"demonstracao_do_resultado":{"periodo":["01/01/2009 a 30/06/2009<","01/01/2008 a 30/06/2008<"],"receitas_da_intermediacao_financeira":[],"resultado_bruto_de_intermediacao_financeira":[],"resultado_operacional":["109.999<","181.149<"],"lucro_liquido":["91.848<","148.068<"]},"demonstracao_do_fluxo_de_caixa":{"periodo":["01/01/2009 a 30/06/2009<","01/01/2008 a 30/06/2008<"],"atividades_operacionais":["130.659<","204.314<"],"atividades_de_investimento":["(159.519)<","(214.165)<"],"atividades_de_financiamento":["(160.432)<","38.273<"],"variacao_cambial_sobre_caixa_e_equivalentes":["(8.767)<","(4.138)<"],"aumento_de_caixa_e_equivalentes":["(198.059)<","24.284<"]},"posicao_acionaria":{"headings":["%ON<","%PN<","%Total<"],"outros":["11,48<","78,78<","50,32<"],"total":["100,00<","100,00<","100,00<"]},"composicao_capital_social":{"data":"31/08/2009","ordinarias":">53.555.963","preferenciais":">73.139.452","total":">126.695.415"}}