{"nome":"FERBASA","cnpj":"15.141.799/0001-03","site":"www.ferbasa.com.br","balanco_patrimonial":{"periodo":["<                    ","31/03/2018<"],"ativo_permanente":[],"ativo_total":["1.919.165<","1.856.461<"],"patromonio_liquido":["1.586.479<","1.522.558<"]},"demonstracao_do_resultado":{"periodo":["01/01/2018 a 31/03/2018<","01/01/2017 a 31/03/2017<"],"receitas_da_intermediacao_financeira":[],"resultado_bruto_de_intermediacao_financeira":[],"resultado_operacional":[],"lucro_liquido":[]},"demonstracao_do_fluxo_de_caixa":{"periodo":["01/01/2018 a 31/03/2018<","01/01/2017 a 31/03/2017<"],"atividades_operacionais":["81.196<","162.263<"],"atividades_de_investimento":["219.318<","1.924<"],"atividades_de_financiamento":["(20.642)<","(55.161)<"],"variacao_cambial_sobre_caixa_e_equivalentes":["0<","0<"],"aumento_de_caixa_e_equivalentes":["279.872<","109.026<"]},"posicao_acionaria":{"headings":["%ON<","%PN<","%Total<"],"outros":["1,06<","65,92<","44,30<"],"total":["100,00<","100,00<","100,00<"]},"composicao_capital_social":{"data":"14/06/18","ordinarias":">313.304","preferenciais":">38.812.100","total":">88.320.000"}}