{"nome":"INDUSVAL","cnpj":"61.024.352/0001-71","site":"www.bip.b.br","balanco_patrimonial":{"periodo":["<                    ","31/03/2017<"],"ativo_permanente":[],"ativo_total":["3.776.348<","3.997.999<"],"patromonio_liquido":["462.192<","493.828<"]},"demonstracao_do_resultado":{"periodo":["01/01/2017 a 31/03/2017<","01/01/2016 a 31/03/2016<"],"receitas_da_intermediacao_financeira":[],"resultado_bruto_de_intermediacao_financeira":["(7.650)<","(5.695)<"],"resultado_operacional":[],"lucro_liquido":[]},"demonstracao_do_fluxo_de_caixa":{"periodo":["01/01/2017 a 31/03/2017<","01/01/2016 a 31/03/2016<"],"atividades_operacionais":["12.995<","96.766<"],"atividades_de_investimento":["(6.122)<","(679)<"],"atividades_de_financiamento":["0<","0<"],"variacao_cambial_sobre_caixa_e_equivalentes":["0<","0<"],"aumento_de_caixa_e_equivalentes":["6.873<","96.087<"]},"posicao_acionaria":{"headings":["%ON<","%PN<","%Total<"],"outros":["19,30<","17,06<","18,75<"],"total":["100,00<","100,00<","100,00<"]},"composicao_capital_social":{"data":"30/05/18","ordinarias":">38.423.435","preferenciais":">29.819.009","total":">152.527.251"}}