{"nome":"SANTANENSE","cnpj":"21.255.567/0001-89","site":"www.santanense.com.br","balanco_patrimonial":{"periodo":["<                    ","31/03/2018<"],"ativo_permanente":[],"ativo_total":["525.546<","513.960<"],"patromonio_liquido":["270.479<","262.641<"]},"demonstracao_do_resultado":{"periodo":["01/01/2018 a 31/03/2018<","01/01/2017 a 31/03/2017<"],"receitas_da_intermediacao_financeira":[],"resultado_bruto_de_intermediacao_financeira":[],"resultado_operacional":[],"lucro_liquido":[]},"demonstracao_do_fluxo_de_caixa":{"periodo":["01/01/2018 a 31/03/2018<","01/01/2017 a 31/03/2017<"],"atividades_operacionais":["17.602<","25.115<"],"atividades_de_investimento":["(3.874)<","(19.818)<"],"atividades_de_financiamento":["(10.604)<","39<"],"variacao_cambial_sobre_caixa_e_equivalentes":["0<","0<"],"aumento_de_caixa_e_equivalentes":["3.124<","5.336<"]},"posicao_acionaria":{"headings":["%ON<","%PN<","%Total<"],"outros":["7,49<","66,32<","9,36<"],"total":["100,00<","100,00<","100,00<"]},"composicao_capital_social":{"data":"30/04/2014","ordinarias":">3.467.284","preferenciais":">1.256.792","total":">39.299.130"}}